salesforce_functions/__init__.py
salesforce_functions/__main__.py
salesforce_functions/__version__.py
salesforce_functions/context.py
salesforce_functions/invocation_event.py
salesforce_functions/py.typed
salesforce_functions/testing.py
salesforce_functions/_internal/__init__.py
salesforce_functions/_internal/app.py
salesforce_functions/_internal/cli.py
salesforce_functions/_internal/cloud_event.py
salesforce_functions/_internal/config.py
salesforce_functions/_internal/function_loader.py
salesforce_functions/_internal/logging.py
salesforce_functions/data_api/__init__.py
salesforce_functions/data_api/_requests.py
salesforce_functions/data_api/exceptions.py
salesforce_functions/data_api/record.py
salesforce_functions/data_api/reference_id.py
salesforce_functions/data_api/unit_of_work.py
salesforce_functions-0.6.0.dist-info/METADATA
salesforce_functions-0.6.0.dist-info/WHEEL
salesforce_functions-0.6.0.dist-info/entry_points.txt
salesforce_functions-0.6.0.dist-info/licenses/LICENSE
salesforce_functions-0.6.0.dist-info/RECORD
