Metadata-Version: 2.1
Name: salesforce-functions
Version: 0.6.0
Summary: Python support for Salesforce Functions
Project-URL: Changelog, https://github.com/heroku/sf-functions-python/blob/main/CHANGELOG.md
Project-URL: Source, https://github.com/heroku/sf-functions-python
License-Expression: BSD-3-Clause
License-File: LICENSE
Keywords: functions,salesforce
Classifier: Programming Language :: Python :: 3.10
Classifier: Programming Language :: Python :: 3.11
Classifier: Programming Language :: Python :: Implementation :: CPython
Requires-Python: >=3.10
Requires-Dist: aiohttp<4,>=3.8.3
Requires-Dist: httptools<0.6,>=0.5.0
Requires-Dist: orjson<4,>=3.8.5
Requires-Dist: python-dateutil<3,>=2.8.2; python_version < '3.11'
Requires-Dist: starlette<0.29,>=0.28.0
Requires-Dist: structlog<24,>=23.1.0
Requires-Dist: tomli<3,>=2.0.1; python_version < '3.11'
Requires-Dist: uvicorn<0.23,>=0.22.0
Requires-Dist: uvloop<0.18,>=0.17.0; sys_platform != 'win32' and sys_platform != 'cygwin'
Provides-Extra: development
Requires-Dist: black==23.3.0; extra == 'development'
Requires-Dist: coverage-conditional-plugin==0.9.0; extra == 'development'
Requires-Dist: flake8==6.0.0; extra == 'development'
Requires-Dist: httpx==0.24.1; extra == 'development'
Requires-Dist: isort[colors]==5.12.0; extra == 'development'
Requires-Dist: mypy==1.4.1; extra == 'development'
Requires-Dist: pylint==2.17.4; extra == 'development'
Requires-Dist: pytest-asyncio==0.21.0; extra == 'development'
Requires-Dist: pytest-cov==4.1.0; extra == 'development'
Requires-Dist: pytest==7.4.0; extra == 'development'
